roblox_open_cloud_api/Enums.py
roblox_open_cloud_api/OpenCloudClient.py
roblox_open_cloud_api/Requests.py
roblox_open_cloud_api/__init__.py
roblox_open_cloud_api-0.0.2.dist-info/LICENSE
roblox_open_cloud_api-0.0.2.dist-info/METADATA
roblox_open_cloud_api-0.0.2.dist-info/WHEEL
roblox_open_cloud_api-0.0.2.dist-info/top_level.txt
roblox_open_cloud_api-0.0.2.dist-info/RECORD
