Metadata-Version: 2.1
Name: roblox-open-cloud-api
Version: 0.0.2
Summary: API for Roblox Open Cloud - DataStores, MessagingService and Place Publishing.
Home-page: UNKNOWN
Author: SPOOK_EXE (Declan H)
Author-email: declagaming@gmail.com
License: MIT
Keywords: python,roblox,open-cloud,roblox open-cloud,datastore,publish,messaging-service
Platform: UNKNOWN
Classifier: Development Status :: 1 - Planning
Classifier: Intended Audience :: Developers
Classifier: Programming Language :: Python :: 3
Classifier: Operating System :: Microsoft :: Windows
Requires-Dist: requests
